LICENSE.md
README.md
pyproject.toml
src/ewoksbm08/__init__.py
src/ewoksbm08.egg-info/PKG-INFO
src/ewoksbm08.egg-info/SOURCES.txt
src/ewoksbm08.egg-info/dependency_links.txt
src/ewoksbm08.egg-info/entry_points.txt
src/ewoksbm08.egg-info/requires.txt
src/ewoksbm08.egg-info/top_level.txt
src/ewoksbm08/io/__init__.py
src/ewoksbm08/io/read_xas.py
src/ewoksbm08/io/save_xas.py
src/ewoksbm08/io/types.py
src/ewoksbm08/tasks/__init__.py
src/ewoksbm08/tasks/read_xas.py
src/ewoksbm08/tasks/save_xas.py
src/ewoksbm08/tests/__init__.py
src/ewoksbm08/tests/conftest.py
src/ewoksbm08/tests/test_convert.py
src/ewoksbm08/tests/test_read_xas.py
src/ewoksbm08/tests/test_save_xas.py
src/ewoksbm08/tests/data/__init__.py
src/ewoksbm08/tests/data/example.h5