Metadata-Version: 2.4
Name: ewoksbm08
Version: 1.0.0
Summary: Data processing workflows for BM08
Author-email: ESRF <dau-pydev@esrf.fr>
License: # MIT License
Project-URL: Homepage, https://gitlab.esrf.fr/workflow/ewoksapps/ewoksbm08/
Project-URL: Documentation, https://ewoksbm08.readthedocs.io/
Project-URL: Repository, https://gitlab.esrf.fr/workflow/ewoksapps/ewoksbm08/
Project-URL: Issues, https://gitlab.esrf.fr/workflow/ewoksapps/ewoksbm08/issues
Project-URL: Changelog, https://gitlab.esrf.fr/workflow/ewoksapps/ewoksbm08/-/blob/main/CHANGELOG.md
Keywords: ewoks
Classifier: Intended Audience :: Science/Research
Classifier: License :: OSI Approved :: MIT License
Classifier: Programming Language :: Python :: 3
Requires-Python: >=3.10
License-File: LICENSE.md
Requires-Dist: ewokscore
Requires-Dist: pydantic
Requires-Dist: blissdata
Provides-Extra: test
Requires-Dist: pytest>=7; extra == "test"
Provides-Extra: dev
Requires-Dist: ewoksbm08[test]; extra == "dev"
Requires-Dist: black>=25; extra == "dev"
Requires-Dist: flake8>=4; extra == "dev"
Requires-Dist: isort; extra == "dev"
Requires-Dist: ruff; extra == "dev"
Requires-Dist: bandit; extra == "dev"
Provides-Extra: doc
Requires-Dist: ewoksbm08[test]; extra == "doc"
Requires-Dist: sphinx>=4.5; extra == "doc"
Requires-Dist: sphinx-autodoc-typehints>=1.16; extra == "doc"
Requires-Dist: pydata-sphinx-theme; extra == "doc"
Requires-Dist: sphinx-copybutton; extra == "doc"
Requires-Dist: ewokssphinx; extra == "doc"
Dynamic: license-file
